{
  "type": "FeatureCollection",
  "features": [
    {
      "type": "Feature",
      "properties": {
        "marker-color": "#259f23",
        "marker-size": "small",
        "marker-symbol": ""
      },
      "geometry": {
        "type": "MultiPoint",
        "coordinates": [
          [
            -73.990746,
            40.749706
          ],
          [
            -73.991325,
            40.750328
          ],
          [
            -73.992729,
            40.749985
          ],
          [
            -73.991608,
            40.74992
          ],
          [
            -73.992645,
            40.750084
          ],
          [
            -73.992256,
            40.749737
          ],
          [
            -73.991943,
            40.750351
          ],
          [
            -73.991554,
            40.749973
          ],
          [
            -73.991325,
            40.750168
          ],
          [
            -73.991653,
            40.74987
          ],
          [
            -73.992363,
            40.749538
          ],
          [
            -73.991539,
            40.750198
          ],
          [
            -73.992287,
            40.749283
          ],
          [
            -73.992233,
            40.749733
          ],
          [
            -73.991386,
            40.750286
          ],
          [
            -73.991501,
            40.750118
          ],
          [
            -73.992294,
            40.749996
          ],
          [
            -73.991768,
            40.749645
          ],
          [
            -73.992058,
            40.749432
          ],
          [
            -73.991043,
            40.749805
          ],
          [
            -73.991447,
            40.750019
          ],
          [
            -73.991928,
            40.75005
          ],
          [
            -73.991142,
            40.750275
          ],
          [
            -73.989952,
            40.750061
          ],
          [
            -73.990341,
            40.75032
          ],
          [
            -73.99221,
            40.749008
          ],
          [
            -73.992241,
            40.749035
          ],
          [
            -73.992104,
            40.748905
          ],
          [
            -73.991844,
            40.748753
          ],
          [
            -73.992302,
            40.748802
          ],
          [
            -73.990379,
            40.751011
          ],
          [
            -73.990601,
            40.751125
          ]
        ]
      }
    },
    {
      "type": "Feature",
      "properties": {
        "marker-color": "#de9a1d",
        "marker-size": "small",
        "marker-symbol": ""
      },
      "geometry": {
        "type": "MultiPoint",
        "coordinates": [
          [
            -73.969673,
            40.757748
          ],
          [
            -73.968948,
            40.758396
          ],
          [
            -73.969765,
            40.75687
          ],
          [
            -73.969933,
            40.757298
          ],
          [
            -73.969711,
            40.757366
          ],
          [
            -73.969131,
            40.757282
          ],
          [
            -73.969742,
            40.758518
          ],
          [
            -73.969688,
            40.757294
          ],
          [
            -73.968941,
            40.758102
          ],
          [
            -73.96965,
            40.757343
          ]
        ]
      }
    },
    {
      "type": "Feature",
      "properties": {
        "marker-color": "#c14f97",
        "marker-size": "small",
        "marker-symbol": ""
      },
      "geometry": {
        "type": "MultiPoint",
        "coordinates": [
          [
            -73.870682,
            40.773678
          ],
          [
            -73.870743,
            40.773758
          ],
          [
            -73.870476,
            40.773727
          ],
          [
            -73.870522,
            40.77383
          ],
          [
            -73.870583,
            40.773838
          ],
          [
            -73.870857,
            40.773815
          ],
          [
            -73.870766,
            40.773857
          ],
          [
            -73.870888,
            40.773312
          ],
          [
            -73.870819,
            40.774113
          ],
          [
            -73.87088,
            40.774109
          ]
        ]
      }
    },
    {
      "type": "Feature",
      "properties": {
        "marker-color": "#3731ff",
        "marker-size": "small",
        "marker-symbol": ""
      },
      "geometry": {
        "type": "MultiPoint",
        "coordinates": [
          [
            -73.97245,
            40.756298
          ],
          [
            -73.972427,
            40.755886
          ],
          [
            -73.972786,
            40.755962
          ],
          [
            -73.971703,
            40.757172
          ],
          [
            -73.973473,
            40.756168
          ],
          [
            -73.972466,
            40.756187
          ],
          [
            -73.973183,
            40.756302
          ],
          [
            -73.972099,
            40.756104
          ],
          [
            -73.972549,
            40.755943
          ],
          [
            -73.972511,
            40.756516
          ],
          [
            -73.972557,
            40.75639
          ],
          [
            -73.973061,
            40.756165
          ],
          [
            -73.972992,
            40.756554
          ],
          [
            -73.972313,
            40.757278
          ],
          [
            -73.972206,
            40.757374
          ],
          [
            -73.972458,
            40.756638
          ],
          [
            -73.972214,
            40.756992
          ],
          [
            -73.97213,
            40.757099
          ],
          [
            -73.971809,
            40.757076
          ],
          [
            -73.972214,
            40.756584
          ],
          [
            -73.972221,
            40.756981
          ],
          [
            -73.971931,
            40.756958
          ],
          [
            -73.97242,
            40.757317
          ],
          [
            -73.971786,
            40.75671
          ],
          [
            -73.97213,
            40.757332
          ],
          [
            -73.971375,
            40.756008
          ],
          [
            -73.972275,
            40.755619
          ],
          [
            -73.972694,
            40.755447
          ],
          [
            -73.973,
            40.755104
          ],
          [
            -73.972145,
            40.755104
          ],
          [
            -73.971962,
            40.755211
          ],
          [
            -73.973907,
            40.75597
          ],
          [
            -73.973381,
            40.755219
          ],
          [
            -73.973816,
            40.756294
          ],
          [
            -73.971794,
            40.757347
          ],
          [
            -73.971382,
            40.757595
          ],
          [
            -73.971207,
            40.756657
          ],
          [
            -73.971886,
            40.757343
          ],
          [
            -73.971115,
            40.757904
          ],
          [
            -73.973541,
            40.757004
          ],
          [
            -73.973923,
            40.75687
          ],
          [
            -73.971169,
            40.75629
          ],
          [
            -73.972824,
            40.757973
          ],
          [
            -73.97126,
            40.755127
          ],
          [
            -73.972008,
            40.754753
          ],
          [
            -73.971672,
            40.755005
          ],
          [
            -73.972183,
            40.754799
          ],
          [
            -73.972717,
            40.754677
          ],
          [
            -73.973541,
            40.754879
          ],
          [
            -73.973434,
            40.75452
          ],
          [
            -73.973801,
            40.754559
          ],
          [
            -73.973175,
            40.754421
          ],
          [
            -73.974106,
            40.755188
          ],
          [
            -73.971222,
            40.75462
          ],
          [
            -73.971474,
            40.754784
          ],
          [
            -73.970917,
            40.755062
          ],
          [
            -73.974701,
            40.756622
          ],
          [
            -73.970116,
            40.756344
          ],
          [
            -73.971573,
            40.754311
          ]
        ]
      }
    },
    {
      "type": "Feature",
      "properties": {
        "marker-color": "#0dbdce",
        "marker-size": "small",
        "marker-symbol": ""
      },
      "geometry": {
        "type": "MultiPoint",
        "coordinates": [
          [
            -73.994171,
            40.751072
          ],
          [
            -73.994232,
            40.75021
          ],
          [
            -73.994949,
            40.750042
          ],
          [
            -73.994705,
            40.750519
          ],
          [
            -73.994415,
            40.750206
          ],
          [
            -73.994659,
            40.750389
          ],
          [
            -73.993996,
            40.750092
          ],
          [
            -73.995117,
            40.750183
          ],
          [
            -73.994621,
            40.750256
          ],
          [
            -73.994339,
            40.75034
          ],
          [
            -73.994354,
            40.749378
          ],
          [
            -73.995361,
            40.749542
          ],
          [
            -73.994164,
            40.751221
          ]
        ]
      }
    },
    {
      "type": "Feature",
      "properties": {
        "marker-color": "#ace213",
        "marker-size": "small",
        "marker-symbol": ""
      },
      "geometry": {
        "type": "MultiPoint",
        "coordinates": [
          [
            -73.978638,
            40.75338
          ],
          [
            -73.97821,
            40.752605
          ],
          [
            -73.977753,
            40.753342
          ],
          [
            -73.977936,
            40.753273
          ],
          [
            -73.978271,
            40.751827
          ],
          [
            -73.977867,
            40.751785
          ],
          [
            -73.978104,
            40.752228
          ],
          [
            -73.979126,
            40.75301
          ],
          [
            -73.977692,
            40.752369
          ],
          [
            -73.979065,
            40.752014
          ]
        ]
      }
    },
    {
      "type": "Feature",
      "properties": {
        "marker-color": "#e30502",
        "marker-size": "small",
        "marker-symbol": ""
      },
      "geometry": {
        "type": "MultiPoint",
        "coordinates": [
          [
            -73.990738,
            40.756306
          ],
          [
            -73.990738,
            40.756187
          ],
          [
            -73.990112,
            40.757065
          ],
          [
            -73.990906,
            40.756092
          ],
          [
            -73.990456,
            40.757156
          ],
          [
            -73.990952,
            40.756207
          ],
          [
            -73.991241,
            40.755951
          ],
          [
            -73.991043,
            40.756474
          ],
          [
            -73.990738,
            40.75629
          ],
          [
            -73.990166,
            40.757
          ],
          [
            -73.990578,
            40.757111
          ],
          [
            -73.990356,
            40.75666
          ],
          [
            -73.99173,
            40.75576
          ],
          [
            -73.98941,
            40.75626
          ]
        ]
      }
    },
    {
      "type": "Feature",
      "properties": {
        "marker-color": "#9f2363",
        "marker-size": "small",
        "marker-symbol": ""
      },
      "geometry": {
        "type": "MultiPoint",
        "coordinates": [
          [
            -73.981934,
            40.762547
          ],
          [
            -73.981888,
            40.762711
          ],
          [
            -73.981804,
            40.76255
          ],
          [
            -73.981773,
            40.76231
          ],
          [
            -73.981796,
            40.762718
          ],
          [
            -73.981743,
            40.762691
          ],
          [
            -73.981682,
            40.763519
          ],
          [
            -73.981804,
            40.762581
          ],
          [
            -73.981575,
            40.762543
          ],
          [
            -73.981812,
            40.763084
          ],
          [
            -73.981972,
            40.76268
          ],
          [
            -73.982101,
            40.762714
          ],
          [
            -73.982544,
            40.762886
          ],
          [
            -73.982193,
            40.763176
          ],
          [
            -73.982262,
            40.762764
          ],
          [
            -73.981956,
            40.762711
          ],
          [
            -73.981964,
            40.762665
          ],
          [
            -73.982101,
            40.762615
          ],
          [
            -73.981949,
            40.762852
          ],
          [
            -73.982361,
            40.762875
          ],
          [
            -73.982048,
            40.762489
          ],
          [
            -73.982124,
            40.762928
          ],
          [
            -73.982109,
            40.76276
          ],
          [
            -73.983307,
            40.762585
          ],
          [
            -73.98278,
            40.763088
          ],
          [
            -73.981339,
            40.762253
          ],
          [
            -73.981743,
            40.763828
          ],
          [
            -73.981056,
            40.764019
          ],
          [
            -73.980606,
            40.763691
          ],
          [
            -73.981277,
            40.763683
          ],
          [
            -73.980782,
            40.763359
          ],
          [
            -73.982887,
            40.761875
          ],
          [
            -73.980278,
            40.762268
          ],
          [
            -73.981041,
            40.76461
          ],
          [
            -73.980896,
            40.764614
          ],
          [
            -73.98069,
            40.764122
          ],
          [
            -73.981262,
            40.764797
          ]
        ]
      }
    },
    {
      "type": "Feature",
      "properties": {
        "marker-color": "#50239f",
        "marker-size": "small",
        "marker-symbol": ""
      },
      "geometry": {
        "type": "MultiPoint",
        "coordinates": [
          [
            -73.872688,
            40.774391
          ],
          [
            -73.872787,
            40.774281
          ],
          [
            -73.872894,
            40.774353
          ],
          [
            -73.872612,
            40.774467
          ],
          [
            -73.872971,
            40.774067
          ],
          [
            -73.87265,
            40.774178
          ],
          [
            -73.872818,
            40.774311
          ],
          [
            -73.872826,
            40.774586
          ],
          [
            -73.872719,
            40.774483
          ],
          [
            -73.872849,
            40.774445
          ],
          [
            -73.872459,
            40.774364
          ],
          [
            -73.872833,
            40.774479
          ],
          [
            -73.87262,
            40.77446
          ]
        ]
      }
    }
  ]
}